setup.py
TracCondFields.egg-info/PKG-INFO
TracCondFields.egg-info/SOURCES.txt
TracCondFields.egg-info/dependency_links.txt
TracCondFields.egg-info/entry_points.txt
TracCondFields.egg-info/requires.txt
TracCondFields.egg-info/top_level.txt
condfields/__init__.py
condfields/web_ui.py
condfields/htdocs/jquery.js
condfields/templates/condfields.js