Metadata-Version: 1.0
Name: TracCondFields
Version: 2.0
Summary: Support for conditional fields in different ticket types.
Home-page: http://trac-hacks.org/wiki/CondFieldsPlugin
Author: Noah Kantrowitz
Author-email: noah@coderanger.net
License: BSD
Keywords: trac plugin ticket conditional fields
Platform: UNKNOWN
Classifier: Framework :: Trac
